python_minifier/__init__.py
python_minifier/__init__.pyi
python_minifier/__main__.py
python_minifier/ast_compare.py
python_minifier/ast_compat.py
python_minifier/ast_printer.py
python_minifier/expression_printer.py
python_minifier/f_string.py
python_minifier/ministring.py
python_minifier/module_printer.py
python_minifier/py.typed
python_minifier/t_string.py
python_minifier/token_printer.py
python_minifier/util.py
python_minifier/ast_annotation/__init__.py
python_minifier/rename/__init__.py
python_minifier/rename/bind_names.py
python_minifier/rename/binding.py
python_minifier/rename/mapper.py
python_minifier/rename/name_generator.py
python_minifier/rename/rename_literals.py
python_minifier/rename/renamer.py
python_minifier/rename/resolve_names.py
python_minifier/rename/util.py
python_minifier/transforms/__init__.py
python_minifier/transforms/combine_imports.py
python_minifier/transforms/constant_folding.py
python_minifier/transforms/remove_annotations.py
python_minifier/transforms/remove_annotations_options.py
python_minifier/transforms/remove_annotations_options.pyi
python_minifier/transforms/remove_asserts.py
python_minifier/transforms/remove_debug.py
python_minifier/transforms/remove_exception_brackets.py
python_minifier/transforms/remove_explicit_return_none.py
python_minifier/transforms/remove_literal_statements.py
python_minifier/transforms/remove_object_base.py
python_minifier/transforms/remove_pass.py
python_minifier/transforms/remove_posargs.py
python_minifier/transforms/suite_transformer.py
python_minifier-3.2.0.dist-info/licenses/LICENSE
python_minifier-3.2.0.dist-info/METADATA
python_minifier-3.2.0.dist-info/WHEEL
python_minifier-3.2.0.dist-info/entry_points.txt
python_minifier-3.2.0.dist-info/top_level.txt
python_minifier-3.2.0.dist-info/zip-safe
python_minifier-3.2.0.dist-info/RECORD
