Metadata-Version: 2.1
Name: python-minifier
Version: 3.2.0
Summary: Transform Python source code into it's most compact representation
Home-page: https://github.com/dflook/python-minifier
Author: Daniel Flook
Author-email: daniel@flook.org
License: MIT
Project-URL: Documentation, https://dflook.github.io/python-minifier/
Project-URL: Issues, https://github.com/dflook/python-minifier/issues
Project-URL: Changelog, https://github.com/dflook/python-minifier/blob/main/CHANGELOG.md
Keywords: minify minifier
Platform: UNKNOWN
Classifier: Development Status :: 5 - Production/Stable
Classifier: License :: OSI Approved :: MIT License
Classifier: Programming Language :: Python
Classifier: Programming Language :: Python :: 3
Classifier: Programming Language :: Python :: 3.3
Classifier: Programming Language :: Python :: 3.4
Classifier: Programming Language :: Python :: 3.5
Classifier: Programming Language :: Python :: 3.6
Classifier: Programming Language :: Python :: 3.7
Classifier: Programming Language :: Python :: 3.8
Classifier: Programming Language :: Python :: 3.9
Classifier: Programming Language :: Python :: 3.10
Classifier: Programming Language :: Python :: 3.11
Classifier: Programming Language :: Python :: 3.12
Classifier: Programming Language :: Python :: 3.13
Classifier: Programming Language :: Python :: 3.14
Classifier: Programming Language :: Python :: 2
Classifier: Programming Language :: Python :: 2.7
Classifier: Programming Language :: Python :: Implementation :: CPython
Classifier: Programming Language :: Python :: Implementation :: PyPy
Classifier: Intended Audience :: Developers
Classifier: Topic :: Software Development
Requires-Python: >=2.7, !=3.0.*, !=3.1.*, !=3.2.*, <3.15
